{
  "offsets_by_season": {
    "2011": {
      "offset": 0.2181485999881485,
      "n": 56,
      "raw_mean_resid": 0.241688534617424
    },
    "2012": {
      "offset": 0.10608991064939155,
      "n": 58,
      "raw_mean_resid": 0.08051696419715881
    },
    "2013": {
      "offset": 0.4437382619239782,
      "n": 51,
      "raw_mean_resid": 0.5801692008972168
    },
    "2014": {
      "offset": 0.0859775169764036,
      "n": 56,
      "raw_mean_resid": 0.05051250383257866
    },
    "2015": {
      "offset": 0.15566433905749708,
      "n": 49,
      "raw_mean_resid": 0.15068739652633667
    },
    "2016": {
      "offset": -0.02605930264008806,
      "n": 69,
      "raw_mean_resid": -0.09543555229902267
    },
    "2017": {
      "offset": 0.33577196408684057,
      "n": 71,
      "raw_mean_resid": 0.3957553505897522
    },
    "2018": {
      "offset": 0.3210430270192599,
      "n": 74,
      "raw_mean_resid": 0.3736186623573303
    },
    "2019": {
      "offset": 0.028152616312062104,
      "n": 87,
      "raw_mean_resid": -0.011291788890957832
    },
    "2020": {
      "offset": 0.03112421035576536,
      "n": 73,
      "raw_mean_resid": -0.01486720610409975
    },
    "2021": {
      "offset": 0.1804792418291694,
      "n": 70,
      "raw_mean_resid": 0.1858578473329544
    }
  },
  "global_offset": 0.16541914641857147,
  "n_samples": 714,
  "min_samples_per_season": 15,
  "shrinkage": 25.0,
  "generated_at": "2026-02-18T20:53:19.593280"
}