{
  "offsets_by_season": {
    "2011": {
      "offset": 0.10741913252110992,
      "n": 59,
      "raw_mean_resid": 0.1415131390094757
    },
    "2012": {
      "offset": -0.055554949132532915,
      "n": 62,
      "raw_mean_resid": -0.0888260081410408
    },
    "2013": {
      "offset": 0.24939352627117914,
      "n": 52,
      "raw_mean_resid": 0.35633403062820435
    },
    "2014": {
      "offset": -0.059130675691579065,
      "n": 59,
      "raw_mean_resid": -0.09560862183570862
    },
    "2015": {
      "offset": 0.14544086375987375,
      "n": 52,
      "raw_mean_resid": 0.20240412652492523
    },
    "2016": {
      "offset": -0.1893537098026656,
      "n": 69,
      "raw_mean_resid": -0.267727255821228
    },
    "2017": {
      "offset": 0.12287365086376668,
      "n": 73,
      "raw_mean_resid": 0.1557217240333557
    }
  },
  "global_offset": 0.026957277208566666,
  "n_samples": 432,
  "min_samples_per_season": 15,
  "shrinkage": 25.0,
  "generated_at": "2026-02-20T19:17:39.437782"
}